README.md
setup.py
TOPSIS_kashish_101803022.egg-info/PKG-INFO
TOPSIS_kashish_101803022.egg-info/SOURCES.txt
TOPSIS_kashish_101803022.egg-info/dependency_links.txt
TOPSIS_kashish_101803022.egg-info/entry_points.txt
TOPSIS_kashish_101803022.egg-info/requires.txt
TOPSIS_kashish_101803022.egg-info/top_level.txt
src/topsispackage.py