Metadata-Version: 2.1
Name: TOPSIS-kashish-101803022
Version: 0.0.2
Summary: A Python package implementing TOPSIS technique.
Home-page: https://pypi.org/project/TOPSIS-kashish-101803022
Author: kashish tayal
Author-email: ktayal_be18@thapar.edu
License: MIT
Platform: UNKNOWN
Classifier: License :: OSI Approved :: MIT License
Classifier: Programming Language :: Python :: 3
Classifier: Programming Language :: Python :: 3.4
Classifier: Programming Language :: Python :: 3.5
Classifier: Programming Language :: Python :: 3.6
Classifier: Programming Language :: Python :: 3.7
